datura_py/__init__.py
datura_py/api.py
datura_py/protocol.py
datura_py/py.typed
datura_py-0.0.16.dist-info/METADATA
datura_py-0.0.16.dist-info/WHEEL
datura_py-0.0.16.dist-info/top_level.txt
datura_py-0.0.16.dist-info/RECORD
